{
	"name": "Darío",
	"type": "dark",
	"colors": {

		// Base colors
		"focusBorder": "#4F46E5",
		"foreground": "#F5F5F5",
		"widget.shadow": "#0000005C",
		"descriptionForeground": "#F5F5F5B3",
		"errorForeground": "#f87171",
		"icon.foreground": "#D4D4D8",
		"sash.hoverBorder": "#4F46E5",

		// Text colors
		"textBlockQuote.background": "#3f3f46",
		"textBlockQuote.border": "#4F46E5",
		"textLink.activeForeground": "#818CF8",
		"textLink.foreground": "#818CF8",
		"textPreformat.foreground": "#fcd34d",

		// Action colors
		"toolbar.hoverBackground": "#6366F180",

		// Button control
		"button.background": "#4F46E5",
		"button.foreground": "#ffffff",
		"button.hoverBackground": "#6366F1",
		"checkbox.background":"#4F46E5",
		"checkbox.foreground":"#F5F5F5",
		"checkbox.border":"#404040",

		// Dropdown control
		"dropdown.background": "#404040",
		"dropdown.foreground": "#FAFAFA",
		"dropdown.border": "#404040",

		// Input control
		"input.background": "#404040",
		"input.foreground": "#F5F5F5",
		"input.placeholderForeground": "#f5f5f580",
		"inputOption.activeBackground": "#4F46E5",
		"inputOption.activeForeground": "#ffffff",
		"inputOption.activeBorder": "#4F46E500",
		"inputValidation.errorBackground": "#7F1D1D",
		"inputValidation.errorBorder": "#B91C1C",
		"inputValidation.errorForeground": "#FCA5A5",
		"inputValidation.infoBackground": "#1e3a8a",
		"inputValidation.infoBorder": "#1D4ED8",
		"inputValidation.infoForeground": "#93C5FD", 
		"inputValidation.warningBackground": "#713F12",
		"inputValidation.warningBorder": "#A16207",
		"inputValidation.warningForeground": "#FDE047",

		// Scrollbar control
		"scrollbar.shadow": "#000000",
		"scrollbarSlider.activeBackground": "#A3A3A366",
		"scrollbarSlider.hoverBackground": "#737373B3",
		"scrollbarSlider.background": "#737373CC",

		// Badge
		"badge.foreground": "#FAFAFA",
		"badge.background": "#404040",

		// Progress bar
		"progressBar.background": "#4F46E5",

		// Lists and trees
		"list.activeSelectionBackground": "#3730A3",
		"list.activeSelectionForeground": "#ffffff",
		"list.activeSelectionIconForeground": "#F5F5F5",
		"list.dropBackground": "#312E81",
		"list.focusHighlightForeground": "#C7D2FE",
		"list.focusOutline": "#3730A3",
		"list.highlightForeground": "#818CF8",
		"list.hoverBackground": "#404040",
		"list.hoverForeground": "#ffffff",
		"list.inactiveSelectionBackground": "#3730A3",
		"list.inactiveSelectionForeground": "#D4D4D8",
		"list.inactiveSelectionIconForeground": "#D4D4D8",
		"list.invalidItemForeground": "#FCD34D",
		"list.errorForeground": "#FCA5A5",
		"list.warningForeground": "#FCD34D",
		"listFilterWidget.background": "#BE123C",
		"listFilterWidget.outline": "#E11D48",
		"listFilterWidget.noMatchesOutline": "#D4D4D8",
		"list.filterMatchBackground": "#EA580C54",
		"list.deemphasizedForeground": "#A3A3A3",
		"tree.indentGuidesStroke": "#525252",
		"tree.tableColumnsBorder": "#F5F5F520",

		// Activity Bar
		"activityBar.background": "#27272A",
		"activityBar.dropBorder": "#4F46E5",
		"activityBar.foreground": "#ffffff",
		"activityBar.inactiveForeground": "#ffffff66",
		"activityBarBadge.background": "#4F46E5",
		"activityBarBadge.foreground": "#EEF2FF",
		"activityBar.activeBorder": "#ffffff",

		// Side Bar
		"sideBar.background": "#27272A",
		"sideBar.foreground": "#F5F5F5",
		"sideBar.border": "#18181B",
		"sideBar.dropBackground": "#71717A80",
		"sideBarTitle.foreground": "#F5F5F5",
		"sideBarSectionHeader.background": "#73737333",
		"sideBarSectionHeader.foreground": "#f5f5f5",

		// Minimap
		"minimap.findMatchHighlight": "#F59E0B",
		"minimap.selectionHighlight": "#0369A1",
		"minimap.errorHighlight": "#B91C1C",
		"minimap.warningHighlight": "#EAB308",
		"minimapSlider.background": "#71717A8C",
		"minimapSlider.hoverBackground": "#A1A1AA8C",
		"minimapSlider.activeBackground": "#A1A1AA8C",
		"minimapGutter.addedBackground": "#4D7C0F",
		"minimapGutter.modifiedBackground": "#0891B2",
		"minimapGutter.deletedBackground": "#991b1b",

		// Editor Groups & Tabs
		"editorGroup.border": "#525252",
		"editorGroup.dropBackground": "#52525b80",
		"editorGroupHeader.noTabsBackground": "#3F3F46",
		"editorGroupHeader.tabsBackground": "#171717",
		"tab.activeBackground": "#52525B",
		"tab.activeForeground": "#ffffff",
		"tab.border": "#27272a",
		"tab.lastPinnedBorder": "#525252",
		"tab.inactiveBackground": "#27272A",
		"tab.unfocusedInactiveBackground": "#27272A",
		"tab.inactiveForeground": "#A1A1AA",
		"tab.unfocusedActiveForeground": "#D4D4D8",
		"tab.unfocusedInactiveForeground": "#A1A1AA",
		"tab.activeModifiedBorder": "#4F46E5",
		"tab.inactiveModifiedBorder": "#4F46E5",
		"tab.unfocusedActiveModifiedBorder": "#71717A",
		"tab.unfocusedInactiveModifiedBorder": "#52525B",

		// Editor colors
		"editor.background": "#27272A",
		"editor.foreground": "#E2E8F0",
		"editorLineNumber.foreground": "#a1a1aa",
		"editorLineNumber.activeForeground": "#818CF8",
		"editorCursor.background": "#525252",
		"editorCursor.foreground": "#D4D4D4",
		"editor.lineHighlightBackground" : "#64748b57",
		"editor.selectionBackground": "#6366F166",
		"editor.inactiveSelectionBackground": "#6366F14D",
		"editor.selectionHighlightBackground": "#6366F14D",
		"editor.selectionHighlightBorder": "#71717A",
		"editor.wordHighlightBackground": "#525252B8",
		"editor.wordHighlightStrongBackground": "#0c4a6eb8",
		"editor.findMatchBackground": "#F973167a",
		"editor.findMatchHighlightBackground": "#EA580C55",
		"editor.findRangeHighlightBackground": "#3f3f4666",
		"searchEditor.findMatchBackground": "#F973167a",
		"editor.hoverHighlightBackground": "#4338CA75",
		"editorLink.activeForeground": "#818CF8",
		"editor.rangeHighlightBackground": "#64748b57",
		"editor.symbolHighlightBackground": "#F973167a",
		"editorWhitespace.foreground": "#E4E4E729",
		"editorIndentGuide.background": "#E4E4E729",
		"editorIndentGuide.activeBackground": "#e4e4e786",
		"editorInlayHint.background": "#ffffff99",
		"editorInlayHint.foreground": "#ffffffcc",
		"editorRuler.foreground": "#52525B",
		"editor.linkedEditingBackground": "#ef44444d",
		"editorLightBulb.foreground": "#FACC15",
		"editorLightBulbAutoFix.foreground": "#60A5FA",
		"editorBracketMatch.background": "#166534ad",
		"editorBracketMatch.border": "#A1A1AA",
		"editorBracketHighlight.foreground1": "#facc15",
		"editorBracketHighlight.foreground2": "#E879F9",
		"editorBracketHighlight.foreground3": "#60a5fa",
		"editorBracketHighlight.unexpectedBracket.foreground": "#EF4444",
		"editor.foldBackground": "#4338CA4D",
		"editorOverviewRuler.border": "#52525B",
		"editorOverviewRuler.findMatchForeground": "#F59E0BB3",
		"editorOverviewRuler.rangeHighlightForeground": "#0369A1B3",
		"editorOverviewRuler.selectionHighlightForeground": "#6366F14D",
		"editorOverviewRuler.wordHighlightForeground": "#525252B8",
		"editorOverviewRuler.wordHighlightStrongForeground": "#0c4a6eb8",
		"editorOverviewRuler.modifiedForeground": "#0891b2",
		"editorOverviewRuler.addedForeground": "#4D7C0F",
		"editorOverviewRuler.deletedForeground": "#991B1B",
		"editorOverviewRuler.errorForeground": "#dc2626b3",
		"editorOverviewRuler.warningForeground": "#f59e0b",
		"editorOverviewRuler.infoForeground": "#0ea5e9",
		"editorOverviewRuler.bracketMatchForeground": "#A1A1AA",
		"editorError.foreground": "#EF4444",
		"editorWarning.foreground": "#FBBF24",
		"editorInfo.foreground": "#0ea5e9",
		"editorHint.foreground": "#F5F5F5B3",
		"problemsErrorIcon.foreground": "#EF4444",
		"problemsWarningIcon.foreground": "#FBBF24",
		"problemsInfoIcon.foreground": "#0ea5e9",
		"editorUnnecessaryCode.opacity": "#00000099",
		"editorGutter.background": "#27272A",
		"editorGutter.modifiedBackground": "#0891b2",
		"editorGutter.addedBackground": "#4D7C0F",
		"editorGutter.deletedBackground": "#991B1B",
		"editorGutter.commentRangeForeground": "#d4d4d4",
		"editorGutter.foldingControlForeground": "#d4d4d4",

		// Diff editor colors
		"diffEditor.insertedTextBackground": "#22c55e33",
		"diffEditor.removedTextBackground": "#ef444433",
		"diffEditor.diagonalFill": "#F5F5F533",

		// Editor widget colors
		"editorWidget.foreground": "#F5F5F5",
		"editorWidget.background": "#171717",
		"editorWidget.border": "#525252",
		"editorWidget.resizeBorder": "#525252",
		"editorSuggestWidget.background": "#171717",
		"editorSuggestWidget.border": "#525252",
		"editorSuggestWidget.foreground": "#F5F5F5",
		"editorSuggestWidget.focusHighlightForeground": "#0EA5E9",
		"editorSuggestWidget.highlightForeground": "#0EA5E9",
		"editorSuggestWidget.selectedBackground": "#3730A3",
		"editorSuggestWidget.selectedForeground": "#ffffff",
		"editorSuggestWidget.selectedIconForeground": "#ffffff",
		"editorHoverWidget.foreground": "#F5F5F5",
		"editorHoverWidget.background": "#171717",
		"editorHoverWidget.border": "#525252",
		"editorGhostText.foreground": "#ffffff56",
		"debugExceptionWidget.background": "#7F1D1D",
		"debugExceptionWidget.border": "#b91c1c",
		"editorMarkerNavigation.background": "#27272A",
		"editorMarkerNavigationError.background": "#EF4444",
		"editorMarkerNavigationWarning.background": "#FBBF24",
		"editorMarkerNavigationInfo.background": "#0ea5e9",
		"editorMarkerNavigationError.headerBackground": "#ef444433",
		"editorMarkerNavigationWarning.headerBackground": "#FBBF2433",
		"editorMarkerNavigationInfo.headerBackground": "#0ea5e933",

		// Peek view colors
		"peekView.border": "#0ea5e9",
		"peekViewEditor.background": "#312e8166",
		"peekViewEditorGutter.background": "#312e8166",
		"peekViewEditor.matchHighlightBackground": "#EA580C55",
		"peekViewResult.background": "#171717",
		"peekViewResult.fileForeground": "#ffffff",
		"peekViewResult.matchHighlightBackground": "#ea580c4d",
		"peekViewResult.selectionBackground": "#6366F166",
		"peekViewResult.selectionForeground": "#ffffff",
		"peekViewTitle.background": "#0ea5e91a",
		"peekViewTitleDescription.foreground": "#F5F5F5B3",
		"peekViewTitleLabel.foreground": "#ffffff",

		// Merge conflicts colors
		"merge.currentHeaderBackground": "#2DD4BF80",
		"merge.currentContentBackground": "#2DD4BF33",
		"merge.incomingHeaderBackground": "#0EA5E980",
		"merge.incomingContentBackground": "#0EA5E933",
		"merge.commonHeaderBackground": "#52525280",
		"merge.commonContentBackground": "#52525233",
		"editorOverviewRuler.currentContentForeground": "#2DD4BF80",
		"editorOverviewRuler.incomingContentForeground": "#0EA5E980",
		"editorOverviewRuler.commonContentForeground": "#52525266",

		// Panel colors
		"panel.background": "#27272A",
		"panel.border": "#73737359",
		"panelTitle.activeBorder": "#E5E5E5",
		"panelTitle.activeForeground": "#E5E5E5",
		"panelTitle.inactiveForeground": "#E5E5E599",
		"panelSection.border": "#73737359",
		"panelSection.dropBackground": "#52525b80",
		"panelSectionHeader.background": "#73737333",
		"panelSectionHeader.foreground": "#F5F5F5",

		// Status Bar colors
		"statusBar.background": "#4F46E5",
		"statusBar.foreground": "#FFFFFF",
		"statusBar.debuggingBackground": "#C2410C",
		"statusBar.debuggingForeground": "#FFFFFF",
		"statusBar.noFolderForeground": "#FFFFFF",
		"statusBar.noFolderBackground": "#701A75",
		"statusBarItem.activeBackground": "#FFFFFF2E",
		"statusBarItem.hoverBackground": "#FFFFFF1F",
		"statusBarItem.remoteBackground": "#4F46E5",
		"statusBarItem.remoteForeground": "#ffffff",
		"statusBarItem.errorBackground": "#7F1D1D",
		"statusBarItem.errorForeground":"#ffffff",
		"statusBarItem.warningBackground": "#f59e0b",
		"statusBarItem.warningForeground": "#ffffff",

		// Title Bar colors
		"titleBar.activeBackground": "#404040",
		"titleBar.inactiveBackground": "#40404099",
		"titleBar.activeForeground": "#F5F5F5",
		"titleBar.inactiveForeground": "#F5F5F599",

		// Menu Bar colors
		"menubar.selectionForeground": "#F5F5F5",
		"menubar.selectionBackground": "#ffffff1A",
		"menu.foreground":"#FAFAFA",
		"menu.background": "#404040",
		"menu.selectionForeground": "#ffffff",
		"menu.selectionBackground": "#3730A3",
		"menu.separatorBackground": "#d4d4d4",

		// Notification colors
		"notificationCenterHeader.background": "#171717",
		"notifications.foreground": "#F5F5F5",
		"notifications.background": "#262626",
		"notificationLink.foreground": "#A5B4FC",
		"notificationsErrorIcon.foreground": "#EF4444",
		"notificationsWarningIcon.foreground": "#f59e0b",
		"notificationsInfoIcon.foreground": "#0ea5e9",

		// Banner colors
		"banner.background": "#3730A3",
		"banner.foreground": "#ffffff",
		"banner.iconForeground": "#0ea5e9",

		// Extensions colors
		"extensionButton.prominentBackground": "#4F46E5",
		"extensionButton.prominentForeground": "#ffffff",
		"extensionButton.prominentHoverBackground": "#6366F1",
		"extensionBadge.remoteBackground": "#4F46E5",
		"extensionBadge.remoteForeground": "#ffffff",
		"extensionIcon.starForeground": "#EAB308",

		// Quick picker colors
		"pickerGroup.border": "#3F3F46",
		"quickInput.background": "#171717",
		"quickInput.foreground": "#F5F5F5",
		"quickInputList.focusBackground": "#4338CA",
		"quickInputList.focusForeground": "#ffffff",
		"quickInputList.focusIconForeground": "#ffffff",
		"quickInputTitle.background": "#ffffff1A",

		// Keybinding label colors
		"keybindingLabel.background": "#7373734D",
		"keybindingLabel.foreground": "#F5F5F5",
		"keybindingLabel.border": "#40404099",
		"keybindingLabel.bottomBorder": "#52525299",

		// Integrated Terminal colors
		"terminal.border": "#73737359",
		"terminal.foreground": "#F5F5F5",
		"terminal.ansiBlack": "#000000",
		"terminal.ansiBlue": "#0284C7",
		"terminal.ansiBrightBlack": "#737373",
		"terminal.ansiBrightBlue": "#38BDF8",
		"terminal.ansiBrightCyan": "#22D3EE",
		"terminal.ansiBrightGreen": "#4ADE80",
		"terminal.ansiBrightMagenta": "#E879F9",
		"terminal.ansiBrightRed": "#F87171",
		"terminal.ansiBrightWhite": "#ffffff",
		"terminal.ansiBrightYellow": "#facc15",
		"terminal.ansiCyan": "#0891B2",
		"terminal.ansiGreen": "#22C55E",
		"terminal.ansiMagenta": "#C026D3",
		"terminal.ansiRed": "#DC2626",
		"terminal.ansiWhite": "#ffffff",
		"terminal.ansiYellow": "#EAB308",
		"terminal.selectionBackground": "#8B5CF64d",
		"terminal.dropBackground": "#52525280",

		// Debug colors
		"debugToolBar.background": "#18181B",
		"debugToolBar.border": "#3F3F46",
		"editor.stackFrameHighlightBackground": "#fbbf2433",
		"editor.focusedStackFrameHighlightBackground": "#4ADE804d",
		"editor.inlineValuesForeground": "#ffffff80",
		"editor.inlineValuesBackground": "#FACC1533",
		"debugView.exceptionLabelForeground": "#F5F5F5",
		"debugView.exceptionLabelBackground": "#BE123C",
		"debugView.stateLabelForeground": "#F5F5F5",
		"debugView.stateLabelBackground": "#a3a3a344",
		"debugView.valueChangedHighlight": "#0ea5e9",
		"debugTokenExpression.name": "#A78BFA",
		"debugTokenExpression.value": "#F5F5F599",
		"debugTokenExpression.boolean": "#06B6D4",
		"debugTokenExpression.error": "#FB7185",
		"debugTokenExpression.number": "#FB923C",
		"debugTokenExpression.string": "#86EFAC",

		// Welcome page colors
		"welcomePage.progress.background": "#404040",
		"welcomePage.progress.foreground": "#818CF8",
		"welcomePage.tileBackground": "#171717",
		"welcomePage.tileHoverBackground": "#17171740",

		// Git colors
		"gitDecoration.addedResourceForeground": "#34D399",
		"gitDecoration.modifiedResourceForeground": "#FB923C",
		"gitDecoration.deletedResourceForeground": "#EF4444",
		"gitDecoration.renamedResourceForeground": "#4ADE80",
		"gitDecoration.stageModifiedResourceForeground": "#FB923C",
		"gitDecoration.stageDeletedResourceForeground": "#EF4444",
		"gitDecoration.untrackedResourceForeground": "#4ADE80",
		"gitDecoration.ignoredResourceForeground": "#A3A3A3",
		"gitDecoration.conflictingResourceForeground": "#fb7185",
		"gitDecoration.submoduleResourceForeground": "#93C5FD",

		// Settings Editor colors
		"settings.headerForeground": "#e5e5e5",
		"settings.modifiedItemIndicator": "#4F46E5",
		"settings.dropdownBackground": "#404040",
		"settings.dropdownForeground": "#F5F5F5",
		"settings.dropdownBorder": "#404040",
		"settings.dropdownListBorder": "#737373",
		"settings.checkboxBackground": "#4F46E5",
		"settings.checkboxForeground": "#F5F5F5",
		"settings.checkboxBorder": "#404040",
		"settings.rowHoverBackground": "#A3A3A31A",
		"settings.textInputBackground": "#404040",
		"settings.textInputForeground": "#f5f5f5",
		"settings.numberInputBackground": "#404040",
		"settings.numberInputForeground": "#f5f5f5",
		"settings.focusedRowBackground": "#A3A3A31A",
		"settings.focusedRowBorder": "#ffffff1F",

		// Breadcrumbs colors
		"breadcrumb.foreground": "#A3A3A3",
		"breadcrumb.background": "#171717",
		"breadcrumb.focusForeground": "#f5f5f5",
		"breadcrumb.activeSelectionForeground": "#f5f5f5",
		"breadcrumbPicker.background": "#171717",

		// Snippets colors
		"editor.snippetTabstopHighlightBackground": "#7373734D",
		"editor.snippetFinalTabstopHighlightBorder": "#6366F1",

		// Symbol Icons colors
		"symbolIcon.arrayForeground": "#f5f5f5",
		"symbolIcon.booleanForeground": "#f5f5f5",
		"symbolIcon.classForeground": "#f59e0b",
		"symbolIcon.colorForeground": "#f5f5f5",
		"symbolIcon.constantForeground": "#f5f5f5",
		"symbolIcon.constructorForeground": "#c084fc",
		"symbolIcon.enumeratorForeground": "#60A5FA",
		"symbolIcon.enumeratorMemberForeground": "#60A5FA",
		"symbolIcon.eventForeground": "#f59e0b",
		"symbolIcon.fieldForeground": "#60A5FA",
		"symbolIcon.fileForeground": "#f5f5f5",
		"symbolIcon.folderForeground": "#f5f5f5",
		"symbolIcon.functionForeground": "#c084fc",
		"symbolIcon.interfaceForeground": "#60A5FA",
		"symbolIcon.keyForeground": "#f5f5f5",
		"symbolIcon.keywordForeground": "#f5f5f5",
		"symbolIcon.methodForeground": "#c084fc",
		"symbolIcon.moduleForeground": "#f5f5f5",
		"symbolIcon.namespaceForeground": "#f5f5f5",
		"symbolIcon.nullForeground": "#f5f5f5",
		"symbolIcon.numberForeground": "#f5f5f5",
		"symbolIcon.objectForeground": "#f5f5f5",
		"symbolIcon.operatorForeground": "#f5f5f5",
		"symbolIcon.packageForeground": "#f5f5f5",
		"symbolIcon.propertyForeground": "#f5f5f5",
		"symbolIcon.referenceForeground": "#f5f5f5",
		"symbolIcon.snippetForeground": "#f5f5f5",
		"symbolIcon.stringForeground": "#f5f5f5",
		"symbolIcon.structForeground": "#f5f5f5",
		"symbolIcon.textForeground": "#f5f5f5",
		"symbolIcon.typeParameterForeground": "#f5f5f5",
		"symbolIcon.unitForeground": "#f5f5f5",
		"symbolIcon.variableForeground": "#60A5FA",

		// Debug Icons colors
		"debugIcon.breakpointForeground": "#dc2626",
		"debugIcon.breakpointDisabledForeground": "#737373",
		"debugIcon.breakpointUnverifiedForeground": "#737373",
		"debugIcon.breakpointCurrentStackframeForeground": "#FACC15",
		"debugIcon.breakpointStackframeForeground": "#86efac",
		"debugIcon.startForeground": "#86efac",
		"debugIcon.pauseForeground": "#60A5FA",
		"debugIcon.stopForeground": "#F87171",
		"debugIcon.disconnectForeground": "#FB7185",
		"debugIcon.restartForeground": "#86efac",
		"debugIcon.stepOverForeground": "#60A5FA",
		"debugIcon.stepIntoForeground": "#60A5FA",
		"debugIcon.stepOutForeground": "#60A5FA",
		"debugIcon.continueForeground": "#60A5FA",
		"debugIcon.stepBackForeground": "#60A5FA",
		"debugConsole.infoForeground": "#0ea5e9",
		"debugConsole.warningForeground": "#f59e0b",
		"debugConsole.errorForeground": "#FB7185",
		"debugConsole.sourceForeground": "#f5f5f5",
		"debugConsoleInputIcon.foreground": "#f5f5f5",

		// Notebook colors
		"notebook.cellBorderColor": "#3730A3",
		"notebook.cellInsertionIndicator": "#4F46E5",
		"notebook.cellStatusBarItemHoverBackground": "#ffffff26",
		"notebook.cellToolbarSeparator": "#73737359",
		"notebook.cellEditorBackground": "#f5f5f50A",
		"notebook.focusedCellBorder": "#4F46E5",
		"notebook.focusedEditorBorder": "#4F46E5",
		"notebook.inactiveFocusedCellBorder": "#3730A3",
		"notebook.selectedCellBackground": "#3730A3",
		"notebook.selectedCellBorder": "#3730A3",
		"notebook.symbolHighlightBackground": "#ffffff0b",
		"notebookScrollbarSlider.activeBackground": "#d4d4d466",
		"notebookScrollbarSlider.background": "#73737366",
		"notebookScrollbarSlider.hoverBackground": "#737373B3",
		"notebookStatusErrorIcon.foreground": "#FB7185",
		"notebookStatusRunningIcon.foreground": "#F5F5F5",
		"notebookStatusSuccessIcon.foreground": "#86efac",

		// Ports Colors
		"ports.iconRunningProcessForeground": "#4F46E5",

	},
	"tokenColors": [
		{
			"name": "Comment",
			"scope": [
				"comment",
				"punctuation.definition.comment"
			],
			"settings": {
				"fontStyle": "italic",
				"foreground": "#64748B"
			}
		},
		{
			"name": "Variables",
			"scope": [
				"variable",
				"string constant.other.placeholder"
			],
			"settings": {
				"foreground": "#E2E8F0"
			}
		},
		{
			"name": "Colors",
			"scope": [
				"constant.other.color"
			],
			"settings": {
				"foreground": "#ffffff"
			}
		},
		{
			"name": "Invalid",
			"scope": [
				"invalid",
				"invalid.illegal"
			],
			"settings": {
				"foreground": "#F87171"
			}
		},
		{
			"name": "Keyword, Storage",
			"scope": [
				"keyword",
				"storage.type",
				"storage.modifier"
			],
			"settings": {
				"foreground": "#d8b4fe"
			}
		},
		{
			"name": "Keyword Operator",
			"scope": [
				"keyword.operator"
			],
			"settings": {
				"foreground": "#14b8a6"
			}
		},
		{
			"name": "Operator, Misc",
			"scope": [
				// "keyword.control",
				"constant.other.color",
				"punctuation",
				"meta.tag",
				"punctuation.definition.tag",
				"punctuation.separator.inheritance.php",
				"punctuation.definition.tag.html",
				"punctuation.definition.tag.begin.html",
				"punctuation.definition.tag.end.html",
				"punctuation.section.embedded",
				"keyword.other.template",
				"keyword.other.substitution"
			],
			"settings": {
				"foreground": "#7dd3fc"
			}
		},
		{
			"name": "Property name CSS",
			"scope": [
				"support.type.property-name.css"
			],
			"settings": {
				"foreground": "#fcd34d"
			}
		},
		{
			"name": "Operator, Misc 2",
			"scope": [
				"keyword.control"
			],
			"settings": {
				"foreground": "#D8B4FE"
			}
		},
		{
			"name": "Tag",
			"scope": [
				"entity.name.tag",
				"meta.tag.sgml",
				"markup.deleted.git_gutter"
			],
			"settings": {
				"foreground": "#f87171"
			}
		},
		{
			"name": "Function, Special Method",
			"scope": [
				"entity.name.function",
				"meta.function-call",
				"variable.function",
				"support.function",
				"keyword.other.special-method"
			],
			"settings": {
				"foreground": "#60A5FA"
			}
		},
		{
			"name": "Block Level Variables",
			"scope": [
				"meta.block variable.other"
			],
			"settings": {
				"foreground": "#E2E8F0"
			}
		},
		{
			"name": "Other Variable, String Link",
			"scope": [
				"support.other.variable",
				"string.other.link"
			],
			"settings": {
				"foreground": "#f87171"
			}
		},
		{
			"name": "Number, Constant, Function Argument, Tag Attribute, Embedded",
			"scope": [
				"constant.numeric",
				"constant.language",
				"support.constant",
				"constant.character",
				"constant.escape",
				"variable.parameter",
				"keyword.other.unit",
				"keyword.other"
			],
			"settings": {
				"foreground": "#FB923C"
			}
		},
		{
			"name": "String, Symbols, Inherited Class, Markup Heading",
			"scope": [
				"string",
				"constant.other.symbol",
				"constant.other.key",
				"entity.other.inherited-class",
				"markup.heading",
				"markup.inserted.git_gutter",
				"meta.group.braces.curly constant.other.object.key.js string.unquoted.label.js"
			],
			"settings": {
				"foreground": "#86efac"
			}
		},
		{
			"name": "Class, Support",
			"scope": [
				"entity.name",
				"support.type",
				"support.class",
				"support.orther.namespace.use.php",
				"meta.use.php",
				"support.other.namespace.php",
				"markup.changed.git_gutter",
				"support.type.sys-types"
			],
			"settings": {
				"foreground": "#fcd34d"
			}
		},
		{
			"name": "Entity Types",
			"scope": [
				"support.type"
			],
			"settings": {
				"foreground": "#FCD34D"
			}
		},
		{
			"name": "CSS Class and Support",
			"scope": [
				"source.css support.type.property-name",
				"source.sass support.type.property-name",
				"source.scss support.type.property-name",
				"source.less support.type.property-name",
				"source.stylus support.type.property-name",
				"source.postcss support.type.property-name"
			],
			"settings": {
				"foreground": "#fcd34d",
			}
		},
		{
			"name": "Sub-methods",
			"scope": [
				"entity.name.module.js",
				"variable.import.parameter.js",
				"variable.other.class.js"
			],
			"settings": {
				"foreground": "#F87171"
			}
		},
		{
			"name": "Language methods",
			"scope": [
				"variable.language"
			],
			"settings": {
				"fontStyle": "italic",
				"foreground": "#F87171"
			}
		},
		{
			"name": "entity.name.method.js",
			"scope": [
				"entity.name.method.js"
			],
			"settings": {
				"fontStyle": "italic",
				"foreground": "#60A5FA"
			}
		},
		{
			"name": "meta.method.js",
			"scope": [
				"meta.class-method.js entity.name.function.js",
				"variable.function.constructor"
			],
			"settings": {
				"foreground": "#60A5FA"
			}
		},
		{
			"name": "Attributes",
			"scope": [
				"entity.other.attribute-name"
			],
			"settings": {
				"foreground": "#d8b4fe"
			}
		},
		{
			"name": "HTML Attributes",
			"scope": [
				"text.html.basic entity.other.attribute-name.html",
				"text.html.basic entity.other.attribute-name"
			],
			"settings": {
				"fontStyle": "italic",
				"foreground": "#fcd34d"
			}
		},
		{
			"name": "CSS Classes",
			"scope": [
				"entity.other.attribute-name.class"
			],
			"settings": {
				"foreground": "#C084FC"
			}
		},
		{
			"name": "CSS ID's",
			"scope": [
				"source.sass keyword.control"
			],
			"settings": {
				"foreground": "#60A5FA"
			}
		},
		{
			"name": "Inserted",
			"scope": [
				"markup.inserted"
			],
			"settings": {
				"foreground": "#86efac"
			}
		},
		{
			"name": "Deleted",
			"scope": [
				"markup.deleted"
			],
			"settings": {
				"foreground": "#F87171"
			}
		},
		{
			"name": "Changed",
			"scope": [
				"markup.changed"
			],
			"settings": {
				"foreground": "#d8b4fe"
			}
		},
		{
			"name": "Regular Expressions",
			"scope": [
				"string.regexp"
			],
			"settings": {
				"foreground": "#7dd3fc"
			}
		},
		{
			"name": "Escape Characters",
			"scope": [
				"constant.character.escape"
			],
			"settings": {
				"foreground": "#7dd3fc"
			}
		},
		{
			"name": "URL",
			"scope": [
				"*url*",
				"*link*",
				"*uri*"
			],
			"settings": {
				"fontStyle": "underline"
			}
		},
		{
			"name": "Decorators",
			"scope": [
				"tag.decorator.js entity.name.tag.js",
				"tag.decorator.js punctuation.definition.tag.js"
			],
			"settings": {
				"fontStyle": "italic",
				"foreground": "#60A5FA"
			}
		},
		{
			"name": "ES7 Bind Operator",
			"scope": [
				"source.js constant.other.object.key.js string.unquoted.label.js"
			],
			"settings": {
				"fontStyle": "italic",
				"foreground": "#F87171"
			}
		},
		{
			"name": "JSON Key - Level 0",
			"scope": [
				"source.json meta.structure.dictionary.json support.type.property-name.json"
			],
			"settings": {
				"foreground": "#fcd34d"
			}
		},
		{
			"name": "JSON Key - Level 1",
			"scope": [
				"source.json meta.structure.dictionary.json meta.structure.dictionary.value.json meta.structure.dictionary.json support.type.property-name.json"
			],
			"settings": {
				"foreground": "#d8b4fe"
			}
		},
		{
			"name": "JSON Key - Level 2",
			"scope": [
				"source.json meta.structure.dictionary.json meta.structure.dictionary.value.json meta.structure.dictionary.json meta.structure.dictionary.value.json meta.structure.dictionary.json support.type.property-name.json"
			],
			"settings": {
				"foreground": "#FB923C"
			}
		},
		{
			"name": "JSON Key - Level 3",
			"scope": [
				"source.json meta.structure.dictionary.json meta.structure.dictionary.value.json meta.structure.dictionary.json meta.structure.dictionary.value.json meta.structure.dictionary.json meta.structure.dictionary.value.json meta.structure.dictionary.json support.type.property-name.json"
			],
			"settings": {
				"foreground": "#F87171"
			}
		},
		{
			"name": "JSON Key - Level 4",
			"scope": [
				"source.json meta.structure.dictionary.json meta.structure.dictionary.value.json meta.structure.dictionary.json meta.structure.dictionary.value.json meta.structure.dictionary.json meta.structure.dictionary.value.json meta.structure.dictionary.json meta.structure.dictionary.value.json meta.structure.dictionary.json support.type.property-name.json"
			],
			"settings": {
				"foreground": "#94A3B8",
			}
		},
		{
			"name": "JSON Key - Level 5",
			"scope": [
				"source.json meta.structure.dictionary.json meta.structure.dictionary.value.json meta.structure.dictionary.json meta.structure.dictionary.value.json meta.structure.dictionary.json meta.structure.dictionary.value.json meta.structure.dictionary.json meta.structure.dictionary.value.json meta.structure.dictionary.json meta.structure.dictionary.value.json meta.structure.dictionary.json support.type.property-name.json"
			],
			"settings": {
				"foreground": "#60A5FA"
			}
		},
		{
			"name": "JSON Key - Level 6",
			"scope": [
				"source.json meta.structure.dictionary.json meta.structure.dictionary.value.json meta.structure.dictionary.json meta.structure.dictionary.value.json meta.structure.dictionary.json meta.structure.dictionary.value.json meta.structure.dictionary.json meta.structure.dictionary.value.json meta.structure.dictionary.json meta.structure.dictionary.value.json meta.structure.dictionary.json meta.structure.dictionary.value.json meta.structure.dictionary.json support.type.property-name.json"
			],
			"settings": {
				"foreground": "#86efac"
			}
		},
		{
			"name": "JSON Key - Level 7",
			"scope": [
				"source.json meta.structure.dictionary.json meta.structure.dictionary.value.json meta.structure.dictionary.json meta.structure.dictionary.value.json meta.structure.dictionary.json meta.structure.dictionary.value.json meta.structure.dictionary.json meta.structure.dictionary.value.json meta.structure.dictionary.json meta.structure.dictionary.value.json meta.structure.dictionary.json meta.structure.dictionary.value.json meta.structure.dictionary.json meta.structure.dictionary.value.json meta.structure.dictionary.json support.type.property-name.json"
			],
			"settings": {
				"foreground": "#fcd34d"
			}
		},
		{
			"name": "JSON Key - Level 8",
			"scope": [
				"source.json meta.structure.dictionary.json meta.structure.dictionary.value.json meta.structure.dictionary.json meta.structure.dictionary.value.json meta.structure.dictionary.json meta.structure.dictionary.value.json meta.structure.dictionary.json meta.structure.dictionary.value.json meta.structure.dictionary.json meta.structure.dictionary.value.json meta.structure.dictionary.json meta.structure.dictionary.value.json meta.structure.dictionary.json meta.structure.dictionary.value.json meta.structure.dictionary.json meta.structure.dictionary.value.json meta.structure.dictionary.json support.type.property-name.json"
			],
			"settings": {
				"foreground": "#d8b4fe"
			}
		},
		{
			"name": "Markdown - Plain",
			"scope": [
				"text.html.markdown",
				"punctuation.definition.list_item.markdown"
			],
			"settings": {
				"foreground": "#e2e8f0",
			}
		},
		{
			"name": "Markdown - Markup Raw Inline",
			"scope": [
				"text.html.markdown markup.inline.raw.markdown"
			],
			"settings": {
				"foreground": "#d8b4fe"
			}
		},
		{
			"name": "Markdown - Markup Raw Inline Punctuation",
			"scope": [
				"text.html.markdown markup.inline.raw.markdown punctuation.definition.raw.markdown"
			],
			"settings": {
				"foreground": "#64748B",
			}
		},
		{
			"name": "Markdown - Heading",
			"scope": [
				"markdown.heading",
				"markup.heading | markup.heading entity.name",
				"markup.heading.markdown punctuation.definition.heading.markdown"
			],
			"settings": {
				"foreground": "#86efac"
			}
		},
		{
			"name": "Markup - Italic",
			"scope": [
				"markup.italic"
			],
			"settings": {
				"fontStyle": "italic",
				"foreground": "#f87171"
			}
		},
		{
			"name": "Markup - Bold",
			"scope": [
				"markup.bold",
				"markup.bold string"
			],
			"settings": {
				"fontStyle": "bold",
				"foreground": "#f87171"
			}
		},
		{
			"name": "Markup - Bold-Italic",
			"scope": [
				"markup.bold markup.italic",
				"markup.italic markup.bold",
				"markup.quote markup.bold",
				"markup.bold markup.italic string",
				"markup.italic markup.bold string",
				"markup.quote markup.bold string"
			],
			"settings": {
				"fontStyle": "bold",
				"foreground": "#f87171"
			}
		},
		{
			"name": "Markup - Underline",
			"scope": [
				"markup.underline"
			],
			"settings": {
				"fontStyle": "underline",
				"foreground": "#FB923C"
			}
		},
		{
			"name": "Markdown - Blockquote",
			"scope": [
				"markup.quote punctuation.definition.blockquote.markdown"
			],
			"settings": {
				"foreground": "#65737E"
			}
		},
		{
			"name": "Markup - Quote",
			"scope": [
				"markup.quote"
			],
			"settings": {
				"fontStyle": "italic"
			}
		},
		{
			"name": "Markdown - Link",
			"scope": [
				"string.other.link.title.markdown"
			],
			"settings": {
				"foreground": "#60A5FA"
			}
		},
		{
			"name": "Markdown - Link Description",
			"scope": [
				"string.other.link.description.title.markdown"
			],
			"settings": {
				"foreground": "#d8b4fe"
			}
		},
		{
			"name": "Markdown - Link Anchor",
			"scope": [
				"constant.other.reference.link.markdown"
			],
			"settings": {
				"foreground": "#fcd34d"
			}
		},
		{
			"name": "Markup - Raw Block",
			"scope": [
				"markup.raw.block"
			],
			"settings": {
				"foreground": "#d8b4fe"
			}
		},
		{
			"name": "Markdown - Raw Block Fenced",
			"scope": [
				"markup.raw.block.fenced.markdown"
			],
			"settings": {
				"foreground": "#00000050"
			}
		},
		{
			"name": "Markdown - Fenced Bode Block",
			"scope": [
				"punctuation.definition.fenced.markdown"
			],
			"settings": {
				"foreground": "#00000050"
			}
		},
		{
			"name": "Markdown - Fenced Bode Block Variable",
			"scope": [
				"markup.raw.block.fenced.markdown",
				"variable.language.fenced.markdown",
				"punctuation.section.class.end"
			],
			"settings": {
				"foreground": "#EEFFFF"
			}
		},
		{
			"name": "Markdown - Fenced Language",
			"scope": [
				"variable.language.fenced.markdown"
			],
			"settings": {
				"foreground": "#65737E"
			}
		},
		{
			"name": "Markdown - Separator",
			"scope": [
				"meta.separator"
			],
			"settings": {
				"fontStyle": "bold",
				"foreground": "#65737E"
			}
		},
		{
			"name": "Markup - Table",
			"scope": [
				"markup.table"
			],
			"settings": {
				"foreground": "#EEFFFF"
			}
		}
	]
}
